shadowbits/__init__.py
shadowbits/cli.py
shadowbits/emb_aud.py
shadowbits/emb_img.py
shadowbits/ext_aud.py
shadowbits/ext_img.py
shadowbits/validator.py
shadowbits/crypto/aes.py
shadowbits-1.0.1.dist-info/licenses/LICENSE
shadowbits-1.0.1.dist-info/METADATA
shadowbits-1.0.1.dist-info/WHEEL
shadowbits-1.0.1.dist-info/entry_points.txt
shadowbits-1.0.1.dist-info/top_level.txt
shadowbits-1.0.1.dist-info/RECORD
