Metadata-Version: 2.4
Name: shadowbits
Version: 1.0.1
Summary: Powerful steganography tool for hiding files in images and audio using LSB techniques
Author-email: kaizoku73 <ultimate0134@gmail.com>
Maintainer-email: kaizoku73 <ultimate0134@gmail.com>
License: MIT
Project-URL: Homepage, https://github.com/kaizoku73/ShadowBits
Project-URL: Repository, https://github.com/kaizoku73/ShadowBits
Project-URL: Bug Reports, https://github.com/kaizoku73/ShadowBits/issues
Project-URL: Documentation, https://kaizoku.gitbook.io/steganography
Project-URL: LSB Image Docs, https://kaizoku.gitbook.io/steganography/lsb-for-image
Project-URL: LSB Audio Docs, https://kaizoku.gitbook.io/steganography/lsb-for-audio
Keywords: steganography,lsb,least-significant-bit,image-steganography,audio-steganography,cryptography,security,png,wav,file-hiding,aes-encryption,bits-manipulation
Classifier: Development Status :: 5 - Production/Stable
Classifier: Intended Audience :: Developers
Classifier: Intended Audience :: End Users/Desktop
Classifier: Topic :: Security :: Cryptography
Classifier: Topic :: Multimedia :: Graphics
Classifier: Topic :: Multimedia :: Sound/Audio
Classifier: Topic :: Software Development :: Libraries :: Python Modules
Classifier: License :: OSI Approved :: MIT License
Classifier: Programming Language :: Python :: 3
Classifier: Programming Language :: Python :: 3.7
Classifier: Programming Language :: Python :: 3.8
Classifier: Programming Language :: Python :: 3.9
Classifier: Programming Language :: Python :: 3.10
Classifier: Programming Language :: Python :: 3.11
Classifier: Programming Language :: Python :: 3.12
Classifier: Operating System :: OS Independent
Requires-Python: >=3.7
License-File: LICENSE
Requires-Dist: future>=0.18.0
Requires-Dist: Pillow>=8.0.0
Requires-Dist: pycryptodome>=3.15.0
Dynamic: license-file
